boonnano/__init__.py
boonnano/expert_client.py
boonnano-3.2.0.dist-info/LICENSE
boonnano-3.2.0.dist-info/METADATA
boonnano-3.2.0.dist-info/WHEEL
boonnano-3.2.0.dist-info/top_level.txt
boonnano-3.2.0.dist-info/RECORD
