Metadata-Version: 2.1
Name: boonnano
Version: 3.2.0
Summary: A SDK package for utilizing the BoonLogic nano API
Home-page: https://github.com/boonlogic/Python_API
Author: BoonLogic
Author-email: elise@boonlogic.com
License: MIT
Classifier: License :: OSI Approved :: MIT License
Classifier: Programming Language :: Python :: 3
Classifier: Operating System :: OS Independent
License-File: LICENSE
Requires-Dist: urllib3
Requires-Dist: numpy
